{"name":"List open cases without cases","testSteps":[{"number":1,"description":"Given There are no open cases","duration":7530,"startTime":1478164041261,"screenshots":[{"screenshot":"2bb57257a99b740ffff2adcfdb4c4730.png"}],"result":"SUCCESS","children":[{"number":2,"description":"Opens the page","duration":4806,"startTime":1478164041450,"screenshots":[{"screenshot":"0b3a20babe07100106d861cc0ad058a3.png"}],"result":"SUCCESS"},{"number":3,"description":"Open case page","duration":2391,"startTime":1478164046259,"screenshots":[{"screenshot":"2bb57257a99b740ffff2adcfdb4c4730.png"}],"result":"SUCCESS"}]},{"number":4,"description":"When I show the list of open cases","duration":64,"startTime":1478164048792,"screenshots":[{"screenshot":"2bb57257a99b740ffff2adcfdb4c4730.png"}],"result":"SUCCESS"},{"number":5,"description":"Then I see an empty list","duration":2180,"startTime":1478164048856,"screenshots":[{"screenshot":"2bb57257a99b740ffff2adcfdb4c4730.png"}],"result":"SUCCESS","children":[{"number":6,"description":"Checks the case list","duration":2119,"startTime":1478164048859,"screenshots":[{"screenshot":"2bb57257a99b740ffff2adcfdb4c4730.png"}],"result":"SUCCESS"}]}],"userStory":{"id":"show-cases","storyName":"Show-cases","path":"stories/manageListOfCases/show/show-cases.story","narrative":"In order to work on cases\nAs a transport specialist\nI want to see a list of open cases","type":"story"},"title":"List open cases without cases","tags":[{"name":"Show/Show cases","type":"story"},{"name":"Manage list of cases/Show","type":"feature"},{"name":"Show-cases","type":"story"},{"name":"Manage list of cases","type":"capability"}],"startTime":1478164041234,"duration":9823,"sessionId":"4c666902-bdb8-4de5-8756-76c91ae3cb93","driver":"firefox","manual":false,"result":"SUCCESS"}